LICENSE
README.md
setup.py
safeconfig/__init__.py
safeconfig/cli_parser.py
safeconfig.egg-info/PKG-INFO
safeconfig.egg-info/SOURCES.txt
safeconfig.egg-info/dependency_links.txt
safeconfig.egg-info/requires.txt
safeconfig.egg-info/top_level.txt
safeconfig/config/__init__.py
safeconfig/config/array.py
safeconfig/config/field.py
safeconfig/config/struct.py
safeconfig/config/variable.py
tests/test_array.py
tests/test_cli_parser.py
tests/test_struct.py
tests/test_variable.py