Metadata-Version: 2.1
Name: safeconfig
Version: 1.0.2
Summary: Structured, flexible, and secure configuration management for Python with CLI support.
Home-page: https://github.com/vahidk/safeconfig
Author: Vahid Kazemi
Author-email: vkazemi@gmail.com
License: MIT
License-File: LICENSE
Requires-Dist: pyyaml
